AUTHORS
CHANGELOG.txt
DESCRIPTION
LICENSE
MANIFEST.in
README.rst
setup.py
django_object_events.egg-info/PKG-INFO
django_object_events.egg-info/SOURCES.txt
django_object_events.egg-info/dependency_links.txt
django_object_events.egg-info/requires.txt
django_object_events.egg-info/top_level.txt
object_events/__init__.py
object_events/admin.py
object_events/app_settings.py
object_events/models.py
object_events/urls.py
object_events/views.py
object_events/management/__init__.py
object_events/management/commands/__init__.py
object_events/management/commands/send_event_emails.py
object_events/migrations/0001_initial.py
object_events/migrations/0002_auto__add_field_objectevent_event_content_type__add_field_objectevent_.py
object_events/migrations/0003_auto__add_field_objectevent_email_sent__add_field_objectevent_read_by_.py
object_events/migrations/0004_auto__del_field_objectevent_type__add_field_objectevent_event_type.py
object_events/migrations/0005_auto__add_field_objectevent_additional_text.py
object_events/migrations/__init__.py
object_events/static/object_events/css/object_events.css
object_events/static/object_events/js/object_events.js
object_events/templates/object_events/notifications.html
object_events/templates/object_events/objectevent_list.html
object_events/templates/object_events/email/body.html
object_events/templates/object_events/email/subject.html
object_events/templates/object_events/partials/notification.html
object_events/templatetags/__init__.py
object_events/templatetags/object_events_tags.py
object_events/tests/__init__.py
object_events/tests/factories.py
object_events/tests/management_tests.py
object_events/tests/models_tests.py
object_events/tests/runtests.py
object_events/tests/south_settings.py
object_events/tests/tags_tests.py
object_events/tests/test_settings.py
object_events/tests/urls.py
object_events/tests/views_tests.py
object_events/tests/test_app/__init__.py
object_events/tests/test_app/models.py
object_events/tests/test_app/templates/404.html
object_events/tests/test_app/templates/base.html
object_events/tests/test_app/templates/test_app/tag.html