Metadata-Version: 1.0
Name: django-object-events
Version: 1.0.4
Summary: Generic app for creating events that can be shown to the user in a notifications list.
